fakeldap.py
fakeldap-0.6.6.dist-info/METADATA
fakeldap-0.6.6.dist-info/WHEEL
fakeldap-0.6.6.dist-info/top_level.txt
fakeldap-0.6.6.dist-info/RECORD
