Metadata-Version: 2.1
Name: fakeldap
Version: 0.6.6
Summary: An implementation of a LDAPObject to fake a ldap server in unittests.
Author-email: Christo Buschek <crito@30loops.net>
Project-URL: homepage, https://github.com/zulip/fakeldap/
Classifier: Development Status :: 4 - Beta
Classifier: Environment :: Console
Classifier: Intended Audience :: Developers
Classifier: License :: OSI Approved :: BSD License
Classifier: Operating System :: OS Independent
Classifier: Programming Language :: Python
Classifier: Programming Language :: Python :: 3
Classifier: Topic :: Software Development :: Testing
Requires-Dist: python-ldap (>=3.4.3)
